streamlit_msal/__init__.py
streamlit_msal/web/.env
streamlit_msal/web/package-lock.json
streamlit_msal/web/package.json
streamlit_msal/web/tsconfig.json
streamlit_msal/web/build/asset-manifest.json
streamlit_msal/web/build/index.html
streamlit_msal/web/build/static/js/839.0552252c.chunk.js
streamlit_msal/web/build/static/js/839.0552252c.chunk.js.LICENSE.txt
streamlit_msal/web/build/static/js/839.0552252c.chunk.js.map
streamlit_msal/web/build/static/js/main.381179f9.js
streamlit_msal/web/build/static/js/main.381179f9.js.LICENSE.txt
streamlit_msal/web/build/static/js/main.381179f9.js.map
streamlit_msal/web/public/index.html
streamlit_msal/web/src/Msal.tsx
streamlit_msal/web/src/index.tsx
streamlit_msal/web/src/react-app-env.d.ts
streamlit_msal-0.1.5.dist-info/METADATA
streamlit_msal-0.1.5.dist-info/WHEEL
streamlit_msal-0.1.5.dist-info/RECORD
