Metadata-Version: 2.1
Name: streamlit-msal
Version: 0.1.5
Summary: Add your description here
Project-URL: Repository, https://github.com/WilianZilv/streamlit_msal
Author-email: Wilian <wilianzilv@gmail.com>
Requires-Python: >=3.8
